noonlight_homeassistant/__init__.py
noonlight_homeassistant/noonlight.py
noonlight_homeassistant-0.0.3.dist-info/LICENSE.txt
noonlight_homeassistant-0.0.3.dist-info/METADATA
noonlight_homeassistant-0.0.3.dist-info/WHEEL
noonlight_homeassistant-0.0.3.dist-info/top_level.txt
noonlight_homeassistant-0.0.3.dist-info/RECORD
