Metadata-Version: 2.1
Name: noonlight-homeassistant
Version: 0.0.3
Summary: Python wrapper for the Noonlight alarm monitoring API, designed for use with a Home Assistant integration.
Home-page: https://github.com/pypa/sampleproject
Author: TJ Davis
Author-email: tjdavisbz@gmail.com
License: UNKNOWN
Project-URL: Bug Tracker, https://github.com/pypa/sampleproject/issues
Platform: UNKNOWN
Classifier: Programming Language :: Python :: 3
Classifier: License :: OSI Approved :: MIT License
Classifier: Operating System :: OS Independent
Requires-Python: >=3.6
